wgtrack/__init__.py
wgtrack/__main__.py
wgtrack/atomicwrite.py
wgtrack/config.py
wgtrack/datakeeper.py
wgtrack/eventprocessor.py
wgtrack/exechelper.py
wgtrack/logic.py
wgtrack/output.py
wgtrack/setupenv.py
wgtrack/wg_command.py
wgtrack/wg_config.py
wgtrack-0.1.11.dist-info/LICENSE
wgtrack-0.1.11.dist-info/METADATA
wgtrack-0.1.11.dist-info/WHEEL
wgtrack-0.1.11.dist-info/entry_points.txt
wgtrack-0.1.11.dist-info/top_level.txt
wgtrack-0.1.11.dist-info/RECORD
