Metadata-Version: 2.1
Name: wgtrack
Version: 0.1.11
Summary: wgtrack tracks WireGuard links, exports the status, and updates endpoints as needed
Home-page: https://www.towalink.net
Author: The Towalink Project
Author-email: pypi.wgtrack@towalink.net
License: UNKNOWN
Project-URL: Repository, https://www.github.com/towalink/wgtrack
Keywords: WireGuard monitoring Towalink VPN dyndns NAT-traversal
Platform: UNKNOWN
Classifier: Programming Language :: Python :: 3
Classifier: License :: OSI Approved :: GNU Affero General Public License v3 or later (AGPLv3+)
Classifier: Operating System :: POSIX :: Linux
Classifier: Development Status :: 4 - Beta
Classifier: Intended Audience :: System Administrators
Classifier: Intended Audience :: Information Technology
Classifier: Intended Audience :: Telecommunications Industry
Classifier: Topic :: System :: Monitoring
Classifier: Topic :: System :: Networking
Requires-Python: >=3.5
